{
  "maharashtra": "Maharashtra",
  "gujarat": "Gujarat",
  "kerala": "Kerala",
  "tamil nadu": "Tamil Nadu",
  "punjab": "Punjab",
  "haryana": "Haryana",
  "2021": "2021",
  "bihar": "Bihar",
  "uttar pradesh": "Uttar Pradesh",
  "karnataka": "Karnataka",
  "telangana": "Telangana",
  "odisha": "Odisha",
  "west bengal": "West Bengal",
  "rajasthan": "Rajasthan",
  "madhya pradesh": "Madhya Pradesh",
  "2020": "2020",
  "goa": "Goa",
  "2018": "2018",
  "june": "June",
  "assam": "Assam",
  "july": "July",
  "2024": "2024",
  "5": "5",
  "2025": "2025",
  "rice": "Rice",
  "millets": "Millets",
  "wheat": "Wheat",
  "sugarcane": "Sugarcane",
  "cotton": "Cotton",
  "drought-resistant": "Drought-resistant",
  "bajra": "Bajra",
  "paddy": "Paddy",
  "pulses": "Pulses"
}